pycoll/__init__.py
pycoll-0.0.2.1.dist-info/LICENSE
pycoll-0.0.2.1.dist-info/METADATA
pycoll-0.0.2.1.dist-info/WHEEL
pycoll-0.0.2.1.dist-info/top_level.txt
pycoll-0.0.2.1.dist-info/RECORD
