Metadata-Version: 2.1
Name: pycoll
Version: 0.0.2.1
Summary: Find Area of Square, Rectangle, Triangle and Parallelogram 
Home-page: https://github.com/sachinshrmaa/pycoll
Author: Sachin Sharma
Author-email: contact@sachinshrmaa.com
License: UNKNOWN
Platform: UNKNOWN
Classifier: Programming Language :: Python :: 3
Classifier: License :: OSI Approved :: MIT License
Classifier: Operating System :: OS Independent
